<?xml version="1.0" encoding="UTF-8"?>
<?xml-stylesheet type="text/xsl" href="forest.xsl"?>
<tree expanded="true" show-heading="true" show-metadata="true" toc="false" root="false"><frontmatter> <anchor>291</anchor>  <taxon>Definition</taxon> <addr>axt-001K</addr>  <route>axt-001K.xml</route> <date><year>2023</year> <month>10</month> <day>24</day></date> <authors><author><link href="tom-de-jong.xml" type="local">Tom de Jong</link></author> </authors> <title>Structurally continuous dcpo</title> <meta name="source"><b>Defn 4.4.1</b> of <link href="tom-de-jong.xml" type="local" title="Tom de Jong">de Jong</link>'s <link href="tdj-thesis.xml" type="local" title="Domain theory in constructive and predicative univalent foundations">PhD thesis</link></meta></frontmatter> <mainmatter><p>  A <tex>\mathcal{V}</tex>-dcpo <tex>D</tex> is <em>structurally continuous</em> if for every <tex>x : D</tex>,
  we have a specified directed <link href="axt-001F.xml" type="local" title="𝓥-Family"><tex>\mathcal{V}</tex>-family</link> <tex>(I,  \alpha )</tex>  satisfying the following conditions.
  <ol>    <li><tex>(I,  \alpha )</tex> is a directed family.</li>    <li><tex>x</tex> is the supremum of <tex>(I,  \alpha )</tex>.</li>    <li>Every <tex>\alpha (i)</tex> given by <tex>(I,  \alpha )</tex> is way below <tex>x</tex>.</li>  </ol></p></mainmatter> <backmatter><contributions/> <context><tree expanded="false" show-heading="true" show-metadata="true" toc="false" root="false"><frontmatter> <anchor>292</anchor>   <addr>axt-0020</addr>  <route>axt-0020.xml</route> <date><year>2023</year> <month>10</month> <day>26</day></date> <authors><author><link href="ayberkt.xml" type="local">Ayberk Tosun</link></author> <contributor><link href="martin-escardo.xml" type="local">Martín H. Escardó</link></contributor><contributor><link href="tom-de-jong.xml" type="local">Tom de Jong</link></contributor></authors> <title>Note on order theory terminology in UF</title> </frontmatter> <mainmatter><p>  In this note, I briefly summarize some discussions that I (<link href="ayberkt.xml" type="local" title="Ayberk Tosun">Ayberk Tosun</link>) have
  had with <link href="tom-de-jong.xml" type="local" title="Tom de Jong">Tom de Jong</link> and <link href="martin-escardo.xml" type="local" title="Martín H. Escardó">Martín Escardó</link> and
  present my proposal for changes to order-theoretic terminology in UF.
</p><p>  Similar order-theoretic terminology is used in
  <ul>    <li>      the work [<link href="tdj-thesis.xml" type="local" title="Domain theory in constructive and predicative univalent foundations">1</link>; <link href="tdj-mhe-aspects.xml" type="local" title="Predicative Aspects of Order Theory in Univalent Foundations">2</link>] <link href="tom-de-jong.xml" type="local" title="Tom de Jong">de Jong</link>      and <link href="martin-escardo.xml" type="local" title="Martín H. Escardó">Escardó</link> on order and domain theory in univalent
      foundations; and
    </li>    <li>      the work [<link href="patch-mfps.xml" type="local" title="Patch Locale of a Spectral Locale in Univalent Type Theory">3</link>] of <link href="ayberkt.xml" type="local" title="Ayberk Tosun">Tosun</link> and
      <link href="martin-escardo.xml" type="local" title="Martín H. Escardó">Escardó</link> on locale theory in univalent foundations.
    </li>  </ul></p><p>  Recall <link href="tom-de-jong.xml" type="local" title="Tom de Jong">de Jong</link> and <link href="martin-escardo.xml" type="local" title="Martín H. Escardó">Escardó</link>'s notion of
  <link href="axt-0021.xml" type="local" title="V-dcpo"><tex>\mathcal{V}</tex>-dcpo</link>.
</p><tree expanded="true" show-heading="true" show-metadata="false" toc="true" root="false"><frontmatter><trail><crumb>1</crumb></trail> <anchor>293</anchor>  <taxon>Definition</taxon> <addr>axt-0021</addr>  <route>axt-0021.xml</route> <date><year>2023</year> <month>10</month> <day>26</day></date> <authors><author><link href="tom-de-jong.xml" type="local">Tom de Jong</link></author><author><link href="martin-escardo.xml" type="local">Martín H. Escardó</link></author> </authors> <title><tex>\mathcal{V}</tex>-dcpo</title> <meta name="source"><b>Defn. 3.2.7</b> of (<link href="tdj-thesis.xml" type="local" title="Domain theory in constructive and predicative univalent foundations">[TdJ]</link>, <link href="https://www.cs.bham.ac.uk//~mhe/TypeTopology/DomainTheory.Basics.Dcpo.html#4941" type="external"><tex>\dagger</tex></link>)</meta></frontmatter> <mainmatter><p>  Let <tex>\mathcal{V}</tex> be a universe. A poset <tex>D</tex> is a <em><tex>\mathcal{V}</tex>-dcpo</em> if the join of
  of every <link href="axt-001F.xml" type="local" title="𝓥-Family"><tex>\mathcal{V}</tex>-family</link> on set <tex>D</tex> exists in <tex>D</tex>.
</p></mainmatter> </tree><p>  The analogous fundamental notion in the work of <link href="ayberkt.xml" type="local" title="Ayberk Tosun">Tosun</link> and
  <link href="martin-escardo.xml" type="local" title="Martín H. Escardó">Escardó</link>'s work on locale theory in UF is that of a <link href="axt-0008.xml" type="local" title="Frame (type-theoretic)"><tex>( \mathcal{U} ,
   \mathcal{V} ,  \mathcal{W} )</tex>-frame</link>.
</p><tree expanded="true" show-heading="true" show-metadata="false" toc="true" root="false"><frontmatter><trail><crumb>2</crumb></trail> <anchor>294</anchor>  <taxon>Definition</taxon> <addr>axt-0008</addr>  <route>axt-0008.xml</route> <date><year>2023</year> <month>8</month> <day>19</day></date> <authors><author><link href="ayberkt.xml" type="local">Ayberk Tosun</link></author><author><link href="martin-escardo.xml" type="local">Martín H. Escardó</link></author> </authors> <title>Frame (type-theoretic)</title> <meta name="source"><b>Defn. 2.4</b> from <link href="patch-mfps.xml" type="local" title="Patch Locale of a Spectral Locale in Univalent Type Theory">Patch Locale of a Spectral Locale in Univalent Type Theory</link></meta></frontmatter> <mainmatter><p>  A <tex>( \mathcal{U} ,  \mathcal{V} ,  \mathcal{W} )</tex>-frame <tex>L</tex> consists of a
  <ol>    <li>a type <tex>|L| :  \mathcal{U}</tex></li>    <li>a partial order <tex>-  \le  - : |L|  \to  |L|  \to   \Omega _{ \mathcal{V} }</tex>,</li>    <li>a top element <tex>\mathbf{1}  : |L|</tex>,</li>    <li>      an operation <tex>-  \wedge  - : |L|  \to  |L|  \to  |L|</tex> giving the greatest lower
      bound <tex>U  \wedge  V</tex> of any two <tex>U, V : |L|</tex>.
    </li>    <li>      an operation <tex>\bigvee  - :  \mathsf{Fam} _{ \mathcal{W} }(|L|)  \to  |L|</tex> giving the least upper
      bound <tex>\bigvee _{i : I} U_i</tex> of any <tex>\mathcal{W}</tex>-family <tex>\left \{  U_i  \right \} _{i : I}</tex>.
    </li>    <li>      such that binary meets distribute over arbitrary joins, i.e.
      <tex display="block">U  \wedge   \bigvee _{i : I} V_i =  \bigvee _{i : I} U  \wedge  V_i</tex>      for every <tex>U : |L|</tex> and <tex>\mathcal{W}</tex>-family <tex>\{  V_i  \} _{i : I}</tex> in <tex>|L|</tex>.
    </li>  </ol></p></mainmatter> </tree><p>  A fundamental notion that arises in both of these lines of research is that
  of a <em>basis</em> for the respective notion of lattice in consideration. Even
  though the notion of lattice in consideration varies, the notion of basis
  does not.
</p><tree expanded="true" show-heading="true" show-metadata="false" toc="true" root="false"><frontmatter><trail><crumb>3</crumb></trail> <anchor>295</anchor>  <taxon>Definition</taxon> <addr>axt-0022</addr>  <route>axt-0022.xml</route> <date><year>2023</year> <month>10</month> <day>26</day></date> <authors><author><link href="ayberkt.xml" type="local">Ayberk Tosun</link></author> </authors> <title>Small intensional basis for a dcpo in UF</title> </frontmatter> <mainmatter><p>  Let <tex>D</tex> be a <link href="axt-0021.xml" type="local" title="V-dcpo"><tex>\mathcal{V}</tex>-dcpo</link>. An <em>intensional basis for <tex>D</tex></em> is a
  <tex>\mathcal{V}</tex>-family <tex>(B,  \beta )</tex> on <tex>D</tex> satisfying the condition: for every
  element <tex>x : D</tex>, there is a specified directed <link href="axt-001F.xml" type="local" title="𝓥-Family"><tex>\mathcal{V}</tex>-family</link>  <tex>(K_x,  \kappa _x)</tex> on the basis index <tex>B</tex> such that
  <tex>x =  \bigvee  (K_x,  \beta   \circ   \kappa _x).</tex></p></mainmatter> </tree><p>  This vanilla notion of basis is not made explicit in <link href="tom-de-jong.xml" type="local" title="Tom de Jong">de Jong</link>'s
  thesis because in domain theory one is usually interested in bases of either
  compact or <em>relatively</em> compact elements meaning bases without these
  conditions do not come up. For the reason behind this, see the <link href="axt-0003.xml" type="local" title="Intuition on the notion of a domain">intuition on
  domains</link>. I find it useful, however, to factor out this notion into
  a definition of its own because it does come up in locale theory and topology.
</p><p>  This is called an “intensional basis” in contrast to an “extensional basis”,
  a notion that none of us have made explicit so far.
</p><p>  In <link href="tom-de-jong.xml" type="local" title="Tom de Jong">de Jong</link>'s thesis, the term “structurally continuous” is used
  for the following notion.
</p><tree expanded="true" show-heading="true" show-metadata="false" toc="true" root="false"><frontmatter><trail><crumb>4</crumb></trail> <anchor>296</anchor>  <taxon>Definition</taxon> <addr>axt-001K</addr>  <route>axt-001K.xml</route> <date><year>2023</year> <month>10</month> <day>24</day></date> <authors><author><link href="tom-de-jong.xml" type="local">Tom de Jong</link></author> </authors> <title>Structurally continuous dcpo</title> <meta name="source"><b>Defn 4.4.1</b> of <link href="tom-de-jong.xml" type="local" title="Tom de Jong">de Jong</link>'s <link href="tdj-thesis.xml" type="local" title="Domain theory in constructive and predicative univalent foundations">PhD thesis</link></meta></frontmatter> <mainmatter><p>  A <tex>\mathcal{V}</tex>-dcpo <tex>D</tex> is <em>structurally continuous</em> if for every <tex>x : D</tex>,
  we have a specified directed <link href="axt-001F.xml" type="local" title="𝓥-Family"><tex>\mathcal{V}</tex>-family</link> <tex>(I,  \alpha )</tex>  satisfying the following conditions.
  <ol>    <li><tex>(I,  \alpha )</tex> is a directed family.</li>    <li><tex>x</tex> is the supremum of <tex>(I,  \alpha )</tex>.</li>    <li>Every <tex>\alpha (i)</tex> given by <tex>(I,  \alpha )</tex> is way below <tex>x</tex>.</li>  </ol></p></mainmatter> </tree><p>  Once the notion of <link href="axt-0022.xml" type="local" title="Small intensional basis for a dcpo in UF">intensional basis</link> has been pinned down, then
  the notion of a structurally continuous dcpo can be expressed simply as a
  <link href="axt-0021.xml" type="local" title="V-dcpo"><tex>\mathcal{V}</tex>-dcpo</link> <tex>D</tex> with an intensional basis <tex>(B,  \beta )</tex>  satisfying the further condition that for every <tex>x  \in  D</tex>, the specified
  covering family <tex>(K_x,  \beta   \circ   \kappa _x)</tex> consists of elements that are
  <em>way below</em> <tex>x</tex> i.e. <tex>\forall  k  \in  K_x. \  \beta ( \kappa _x(k))  \ll  x</tex>.
</p><p>  The new term that we will be using for this is “intensionally continuous
  dcpo”.
</p></mainmatter> </tree></context> <related><tree expanded="false" show-heading="true" show-metadata="true" toc="false" root="false"><frontmatter> <anchor>297</anchor>  <taxon>Definition</taxon> <addr>axt-001F</addr>  <route>axt-001F.xml</route> <date><year>2023</year> <month>10</month> <day>16</day></date> <authors><author>Ayberk Tosun</author> </authors> <title>𝓥-Family</title> </frontmatter> <mainmatter><p>  A <em><tex>\mathcal{V}</tex>-family on a type <tex>A :  \mathcal{U}</tex></em> is a pair <tex>(I,  \iota )</tex> where
  <ul>    <li><tex>I</tex> is a type in universe <tex>\mathcal{V}</tex>,</li>    <li>and <tex>\iota</tex> is a function of type <tex>I  \to  A</tex>.</li>  </ul></p><p>  List of formal definitions:
  <ol>    <li>      <link href="https://www.cs.bham.ac.uk//~mhe/TypeTopology/Slice.Family.html#262" type="external">Fam in UF.Slice</link>      in TypeTopology.
    </li>  </ol></p></mainmatter> </tree><tree expanded="false" show-heading="true" show-metadata="true" toc="false" root="false"><frontmatter> <anchor>298</anchor>  <taxon>Person</taxon> <addr>tom-de-jong</addr>  <route>tom-de-jong.xml</route>   <title>Tom de Jong</title> <meta name="orcid">0000-0003-1585-3172</meta><meta name="external">https://tdejong.com/</meta></frontmatter> <mainmatter/> </tree></related> <backlinks><tree expanded="false" show-heading="true" show-metadata="true" toc="false" root="false"><frontmatter> <anchor>299</anchor>  <taxon>Definition</taxon> <addr>axt-0027</addr>  <route>axt-0027.xml</route> <date><year>2023</year> <month>10</month> <day>28</day></date> <authors><author><link href="tom-de-jong.xml" type="local">Tom de Jong</link></author> </authors> <title>Continuous dcpo in UF</title> <meta name="source"><b>Defn. 4.4.5</b> of <link href="tom-de-jong.xml" type="local" title="Tom de Jong">TdJ</link>'s <link href="tdj-thesis.xml" type="local" title="Domain theory in constructive and predicative univalent foundations">thesis</link></meta></frontmatter> <mainmatter><p>  A <link href="axt-0021.xml" type="local" title="V-dcpo"><tex>\mathcal{V}</tex>-dcpo</link> is called <em>continuous</em> if the propositional
  truncation of its <link href="axt-001K.xml" type="local" title="Structurally continuous dcpo">structural continuity</link> holds.
</p></mainmatter> </tree></backlinks> <references><tree expanded="false" show-heading="true" show-metadata="true" toc="false" root="false"><frontmatter> <anchor>300</anchor>  <taxon>Reference</taxon> <addr>tdj-thesis</addr>  <route>tdj-thesis.xml</route> <date><year>2023</year>  </date> <authors><author><link href="tom-de-jong.xml" type="local">Tom de Jong</link></author> </authors> <title>Domain theory in constructive and predicative univalent foundations</title> <meta name="bibtex">@phdthesis{tdj-thesis,
  title     = {Domain theory in constructive and predicative univalent foundations},
  author    = {de Jong, Tom},
  date      = {2023},
  school    = {University of Birmingham},
  location  = {Birmingham, UK},
  uri       = {http://etheses.bham.ac.uk/id/eprint/13401},
}
</meta></frontmatter> <mainmatter/> </tree></references></backmatter></tree>