<?xml version="1.0" encoding="UTF-8"?>
<?xml-stylesheet type="text/xsl" href="forest.xsl"?>
<tree expanded="true" show_heading="true" show_metadata="true" toc="false" root="false" taxon="Reference"><frontmatter> <anchor>334</anchor> <addr>manuell-pointfree-topology-and-constructive-mathematics-2023</addr> <sourcePath>/Users/ayberkt/Code/mathematical-forest/trees/refs/manuell-pointfree-topology-and-constructive-mathematics-2023.tree</sourcePath> <route>manuell-pointfree-topology-and-constructive-mathematics-2023.xml</route> <date>2023</date> <authors><author>Graham Manuell</author> </authors> <title>Pointfree topology and constructive mathematics</title> <meta name="bibtex">@misc{manuell-pt-and-cm-2023,
   title    = {Pointfree topology and constructive mathematics}, 
   author   = {Graham Manuell},
   date     = {2023-04-12},
   eprint   = {2304.06000},
}
</meta></frontmatter> <mainmatter/> <backmatter><contributions/> <context/> <related/> <backlinks><tree expanded="false" show_heading="true" show_metadata="true" toc="false" root="false"><frontmatter> <anchor>336</anchor> <addr>axt-000T</addr> <sourcePath>/Users/ayberkt/Code/mathematical-forest/trees/axt-000T.tree</sourcePath> <route>axt-000T.xml</route> <date>September 17, 2023</date> <authors><author>Ayberk Tosun</author> </authors> <title>Brouwerian counterexample</title> </frontmatter> <mainmatter><p>  A <em>Brouwerian counterexample</em> is a proof that a statement implies some
  nonconstructive principle.
</p><p>  Remark 1.6 from
  <link href="manuell-pointfree-topology-and-constructive-mathematics-2023.xml" type="local" title="Pointfree topology and constructive mathematics">Manuell</link>.
</p></mainmatter> </tree><tree expanded="false" show_heading="true" show_metadata="true" toc="false" root="false"><frontmatter> <anchor>338</anchor> <addr>axt-000U</addr> <sourcePath>/Users/ayberkt/Code/mathematical-forest/trees/axt-000U.tree</sourcePath> <route>axt-000U.xml</route> <date>September 17, 2023</date> <authors><author>Ayberk Tosun</author> </authors> <title>Sierpiński frame</title> </frontmatter> <mainmatter><p>  The <em>Sierpiński frame</em> is the <link href="axt-000V.xml" type="local" title="Free frame">free frame</link> on one generator.
</p><p>  Its points correspond to the elements of the initial frame, <tex>\Omega</tex>.
</p><p>  From pg. 10 of <link href="manuell-pointfree-topology-and-constructive-mathematics-2023.xml" type="local" title="Pointfree topology and constructive mathematics">Manuell</link>.
</p></mainmatter> </tree></backlinks> <references/></backmatter></tree>